causar/__init__.py
causar/cache.py
causar/causar.py
causar/exceptions.py
causar/faker.py
causar/injection.py
causar/injection_metadata.py
causar/overloads/__init__.py
causar/overloads/text_channel.py
causar/transaction_base.py
causar/transaction_types.py
causar/transactions/__init__.py
causar/transactions/fetch_channel.py
causar/transactions/interaction_followup_send.py
causar/transactions/interaction_response_sent.py
causar/transactions/message_sent.py
causar/typings/__init__.py
causar/typings/overwrites.py
causar/typings/ui.py
causar-0.2.0.dist-info/LICENSE
causar-0.2.0.dist-info/WHEEL
causar-0.2.0.dist-info/METADATA
causar-0.2.0.dist-info/RECORD
