Metadata-Version: 2.1
Name: causar
Version: 0.2.0
Summary: A high level testing framework for Disnake bots
Home-page: https://github.com/Skelmis/Causar
Author: Skelmis
Author-email: ethan@koldfusion.xyz
Requires-Python: >=3.10,<4.0
Classifier: Programming Language :: Python :: 3
Classifier: Programming Language :: Python :: 3.10
Requires-Dist: disnake (>=2.5.2,<3.0.0)
Project-URL: Repository, https://github.com/Skelmis/Causar
